sdgp/__init__.py
sdgp/__main__.py
sdgp/Gtk/__init__.py
sdgp-0.96.1.dist-info/licenses/LICENSE
sdgp-0.96.1.dist-info/licenses/LICENSE.GPLv3
sdgp-0.96.1.dist-info/licenses/LICENSE.RPTv1
sdgp-0.96.1.dist-info/METADATA
sdgp-0.96.1.dist-info/WHEEL
sdgp-0.96.1.dist-info/top_level.txt
sdgp-0.96.1.dist-info/zip-safe
sdgp-0.96.1.dist-info/RECORD
