Metadata-Version: 2.4
Name: sdgp
Version: 0.96.1
Summary: sdgp - Stable Diffusion Get Prompt
Author: Twinkle Computing
Author-email: Twinkle Computing <twinkle@twinkle.work>
License-Expression: GPL-3.0-or-later AND LicenseRef-ResistPsychiatricTerror-1.0-or-later
Project-URL: Homepage, https://github.com/ScrapWareOrg/sdgp
Project-URL: Issues, https://github.com/ScrapWareOrg/sdgp/issues
Classifier: Operating System :: OS Independent
Requires-Python: >=3.9
License-File: LICENSE
License-File: LICENSE.GPLv3
License-File: LICENSE.RPTv1
Dynamic: license-file
